cli/__init__.py
cli/cli.py
devops_project_generator-1.5.0.dist-info/licenses/LICENSE
generator/__init__.py
generator/config.py
generator/config_generator.py
generator/generator.py
generator/scanner.py
devops_project_generator-1.5.0.dist-info/METADATA
devops_project_generator-1.5.0.dist-info/WHEEL
devops_project_generator-1.5.0.dist-info/entry_points.txt
devops_project_generator-1.5.0.dist-info/top_level.txt
devops_project_generator-1.5.0.dist-info/RECORD
